core/__init__.py
core/exceptions.py
stock_time_series/__init__.py
stock_time_series/stock_series.py
alphav_pkg-1.0.0.dist-info/METADATA
alphav_pkg-1.0.0.dist-info/WHEEL
alphav_pkg-1.0.0.dist-info/top_level.txt
alphav_pkg-1.0.0.dist-info/RECORD
